presage_technologies/__init__.py
presage_technologies/physiology.py
Presage_Technologies-1.6.0.dist-info/LICENSE.txt
Presage_Technologies-1.6.0.dist-info/METADATA
Presage_Technologies-1.6.0.dist-info/WHEEL
Presage_Technologies-1.6.0.dist-info/top_level.txt
Presage_Technologies-1.6.0.dist-info/RECORD
