Metadata-Version: 2.1
Name: Presage-Technologies
Version: 1.6.0
Summary: A Python client to interface with Presage Technologies' API services.
Home-page: https://physiology.presagetech.com/
Author: Presage Technologies
Author-email: support@presagetech.com
License: UNKNOWN
Project-URL: Bug Tracker, https://github.com/Presage-Security/presage_technologies/issues
Platform: UNKNOWN
Classifier: Programming Language :: Python :: 3
Classifier: License :: OSI Approved :: MIT License
Classifier: Operating System :: OS Independent
Requires-Python: >=3.6
Requires-Dist: requests
Requires-Dist: presage-physiology-preprocessing ==1.2.6
Requires-Dist: mediapipe ==0.9.1.0
Requires-Dist: numpy ==1.26.3
